texture_courier/__init__.py
texture_courier/api.py
texture_courier/cli.py
texture_courier/core.py
texture_courier/find.py
texture_courier/signal.py
texture_courier/util.py
texture_courier-0.0.11.dist-info/LICENSE
texture_courier-0.0.11.dist-info/METADATA
texture_courier-0.0.11.dist-info/WHEEL
texture_courier-0.0.11.dist-info/entry_points.txt
texture_courier-0.0.11.dist-info/top_level.txt
texture_courier-0.0.11.dist-info/RECORD
