Metadata-Version: 2.1
Name: texture-courier
Version: 0.0.11
Summary: rips texture cache from second life viewers
Author-email: Merilynn Bandy <hello@furudean.com>
Project-URL: Homepage, https://github.com/furudean/texture-courier
Project-URL: Issues, https://github.com/furudean/texture-courier/issues
Classifier: Programming Language :: Python :: 3
Classifier: License :: OSI Approved :: MIT License
Classifier: Operating System :: OS Independent
Requires-Python: >=3.11
License-File: LICENSE
Requires-Dist: Pillow >=10
Requires-Dist: tqdm >=4
Requires-Dist: watchdog >=3
Provides-Extra: dev
Requires-Dist: mypy >=1 ; extra == 'dev'
Requires-Dist: flake8 >=6 ; extra == 'dev'
Requires-Dist: types-setuptools ; extra == 'dev'
Requires-Dist: types-Pillow >=10 ; extra == 'dev'
Requires-Dist: types-tqdm >=4 ; extra == 'dev'
